osscore/__init__.py
osscore/core.py
osscore/exceptions.py
osscore-0.1.3.dist-info/WHEEL
osscore-0.1.3.dist-info/METADATA
osscore-0.1.3.dist-info/RECORD
