Metadata-Version: 2.1
Name: osscore
Version: 0.1.3
Summary: 
Author: similarface
Requires-Python: >=3.8,<4.0
Classifier: Programming Language :: Python :: 3
Classifier: Programming Language :: Python :: 3.8
Classifier: Programming Language :: Python :: 3.9
Classifier: Programming Language :: Python :: 3.10
Requires-Dist: aliyun-python-sdk-core (>=2.13.36,<3.0.0)
Requires-Dist: aliyun-python-sdk-sts (>=3.1.0,<4.0.0)
Requires-Dist: oss2 (>=2.16.0,<3.0.0)
